{
  "page": 409,
  "total_results": 10000,
  "total_pages": 500,
  "results": [
    {
      "id": 116612,
      "name": "Josephine Bornebusch",
      "profile_path": "/nba2j9kEqZrFI1VdoYNXxWeK2Mv.jpg",
      "popularity": 7.083,
      "adult": false,
      "known_for_department": "Acting"
    },
    {
      "id": 205772,
      "name": "Wrenn Schmidt",
      "profile_path": "/inW0aDzK6G7Uin529nEsocCgl8Q.jpg",
      "popularity": 7.082,
      "adult": false,
      "known_for_department": "Acting"
    },
    {
      "id": 21710,
      "name": "Michael O'Neill",
      "profile_path": "/u9Ejl9iS4ZJ36Y653UCe8huLaOn.jpg",
      "popularity": 7.082,
      "adult": false,
      "known_for_department": "Acting"
    },
    {
      "id": 3132668,
      "name": "Moon Sang-min",
      "profile_path": "/o5arBU0ZjmjvvdLp2JscIcFmOqQ.jpg",
      "popularity": 7.078,
      "adult": false,
      "known_for_department": "Acting"
    },
    {
      "id": 8397,
      "name": "Charlie Creed-Miles",
      "profile_path": "/lb8m259EJs7UHz447m3ChyqomvZ.jpg",
      "popularity": 7.078,
      "adult": false,
      "known_for_department": "Acting"
    },
    {
      "id": 131935,
      "name": "Dorian Brown Pham",
      "profile_path": "/i4RjpHv6SbDl1meOKjmAd1IsEiF.jpg",
      "popularity": 7.077,
      "adult": false,
      "known_for_department": "Acting"
    },
    {
      "id": 28626,
      "name": "Arielle Dombasle",
      "profile_path": "/yzrLz3f4uXsiEJeG5FRiIqbGKPS.jpg",
      "popularity": 7.077,
      "adult": false,
      "known_for_department": "Acting"
    },
    {
      "id": 10160,
      "name": "Rhonda Fleming",
      "profile_path": "/d3HdasenzxjmfLo2FRc2iKOg2U5.jpg",
      "popularity": 7.077,
      "adult": false,
      "known_for_department": "Acting"
    },
    {
      "id": 2275,
      "name": "Caitlin Clarke",
      "profile_path": "/59PKSNwM5Czk3XWDIsHnBMbiIOz.jpg",
      "popularity": 7.076,
      "adult": false,
      "known_for_department": "Acting"
    },
    {
      "id": 1383137,
      "name": "Inma Cuevas",
      "profile_path": "/y8JsBIOjnA00nBLrloUEhb0eXRD.jpg",
      "popularity": 7.074,
      "adult": false,
      "known_for_department": "Acting"
    },
    {
      "id": 143081,
      "name": "Oja Kodar",
      "profile_path": "/yLVbszgg91tvFjqYUzHB0fI5Wa0.jpg",
      "popularity": 7.074,
      "adult": false,
      "known_for_department": "Acting"
    },
    {
      "id": 34551,
      "name": "Reece Shearsmith",
      "profile_path": "/fEpejkayrwRoFYcRd1xamhivxnq.jpg",
      "popularity": 7.074,
      "adult": false,
      "known_for_department": "Acting"
    },
    {
      "id": 1078814,
      "name": "Tuncer Salman",
      "profile_path": "/teqT0VjctqtwPorYM5IB0d9129g.jpg",
      "popularity": 7.073,
      "adult": false,
      "known_for_department": "Acting"
    },
    {
      "id": 46929,
      "name": "Ivonne Coll",
      "profile_path": "/7cyzeWeX8zD4IwAUDfyE9BK8woY.jpg",
      "popularity": 7.073,
      "adult": false,
      "known_for_department": "Acting"
    },
    {
      "id": 71158,
      "name": "Lars Mikkelsen",
      "profile_path": "/uUBFJk4IB4EsY63f69dP3im6FkE.jpg",
      "popularity": 7.072,
      "adult": false,
      "known_for_department": "Acting"
    },
    {
      "id": 1349948,
      "name": "Rin Ogawa",
      "profile_path": "/ipmNMTC8DUeshzsXi9HwzHvXjwj.jpg",
      "popularity": 7.07,
      "adult": false,
      "known_for_department": "Acting"
    },
    {
      "id": 1093765,
      "name": "Minami Matsuzaka",
      "profile_path": "/eXxIKSwx6ykK5XbRjq1eXzYeiiv.jpg",
      "popularity": 7.07,
      "adult": false,
      "known_for_department": "Acting"
    },
    {
      "id": 111989,
      "name": "Jack Cassidy",
      "profile_path": "/33vNXGeguCsWOIcmy9PfkAb7CEK.jpg",
      "popularity": 7.07,
      "adult": false,
      "known_for_department": "Acting"
    },
    {
      "id": 4969,
      "name": "Lionel Stander",
      "profile_path": "/t2KrtknCJd5zsXWmMH089z5ePbT.jpg",
      "popularity": 7.068,
      "adult": false,
      "known_for_department": "Acting"
    },
    {
      "id": 2030076,
      "name": "Sadie Stanley",
      "profile_path": "/tBijc7eYGJCPVS818rAcJJwAWBr.jpg",
      "popularity": 7.067,
      "adult": false,
      "known_for_department": "Acting"
    }
  ]
}