{
  "page": 420,
  "total_results": 10000,
  "total_pages": 500,
  "results": [
    {
      "id": 1343865,
      "name": "Salvatore Esposito",
      "profile_path": "/lvTeMD1NqYmYbaH0jYek2oXaSvR.jpg",
      "popularity": 8.702,
      "adult": false,
      "known_for_department": "Acting"
    },
    {
      "id": 222340,
      "name": "Yuhko Kaida",
      "profile_path": "/wttsRGyYySLPfNcDtAbNLVizHLx.jpg",
      "popularity": 8.702,
      "adult": false,
      "known_for_department": "Acting"
    },
    {
      "id": 30615,
      "name": "Robert DoQui",
      "profile_path": "/uLQsWehFSYRn2LNfzT9fUjSRpkF.jpg",
      "popularity": 8.702,
      "adult": false,
      "known_for_department": "Acting"
    },
    {
      "id": 1031067,
      "name": "Sonequa Martin-Green",
      "profile_path": "/anz0LIPc0KarbDwLOyGt21eolvK.jpg",
      "popularity": 8.701,
      "adult": false,
      "known_for_department": "Acting"
    },
    {
      "id": 62644,
      "name": "50 Cent",
      "profile_path": "/uyEfYdXj8lJusUyH7I7ChvhDXPH.jpg",
      "popularity": 8.7,
      "adult": false,
      "known_for_department": "Acting"
    },
    {
      "id": 55635,
      "name": "Jaclyn Smith",
      "profile_path": "/ssDofPx6EStJARAwuIhGylloCmj.jpg",
      "popularity": 8.7,
      "adult": false,
      "known_for_department": "Acting"
    },
    {
      "id": 224185,
      "name": "James Maslow",
      "profile_path": "/yWU57nqz43oD0Hk7ZVffEyTgN0x.jpg",
      "popularity": 8.699,
      "adult": false,
      "known_for_department": "Acting"
    },
    {
      "id": 14407,
      "name": "Matt LeBlanc",
      "profile_path": "/llINftOQFR6B9v1f4XFCJiRMi2P.jpg",
      "popularity": 8.699,
      "adult": false,
      "known_for_department": "Acting"
    },
    {
      "id": 3090,
      "name": "Richard Conte",
      "profile_path": "/pTTzNets0bgWAqx18D7by0hWUea.jpg",
      "popularity": 8.699,
      "adult": false,
      "known_for_department": "Acting"
    },
    {
      "id": 383,
      "name": "Michael Palin",
      "profile_path": "/7qCp6M2NxMWpUmO2t6IqHGNlBjz.jpg",
      "popularity": 8.699,
      "adult": false,
      "known_for_department": "Acting"
    },
    {
      "id": 1330527,
      "name": "Lily Mo Sheen",
      "profile_path": "/kKp26B42mkJweUeQtvZXvtuZuSZ.jpg",
      "popularity": 8.698,
      "adult": false,
      "known_for_department": "Acting"
    },
    {
      "id": 165424,
      "name": "Danny Sapani",
      "profile_path": "/h6goTpKA74Z6ePB2BAEEyQnGtCF.jpg",
      "popularity": 8.695,
      "adult": false,
      "known_for_department": "Acting"
    },
    {
      "id": 1644758,
      "name": "Ivan Mulin",
      "profile_path": "/u9bolDJkBoR9AaFCuzzfQW6MpwK.jpg",
      "popularity": 8.694,
      "adult": false,
      "known_for_department": "Acting"
    },
    {
      "id": 1199734,
      "name": "Alexandre Landry",
      "profile_path": "/i8NFDsPfE5xzXuQW93RjqUBNTT1.jpg",
      "popularity": 8.693,
      "adult": false,
      "known_for_department": "Acting"
    },
    {
      "id": 934801,
      "name": "Natasza Urbańska",
      "profile_path": "/56Nc4WIey8Qhkf6QUgv1VnmRJJr.jpg",
      "popularity": 8.693,
      "adult": false,
      "known_for_department": "Acting"
    },
    {
      "id": 185504,
      "name": "Joy Osmanski",
      "profile_path": "/xoRSO5b7hWN9i42fFEswHwStLEI.jpg",
      "popularity": 8.692,
      "adult": false,
      "known_for_department": "Acting"
    },
    {
      "id": 1875842,
      "name": "Rosé",
      "profile_path": "/d3EdgHVIDuxN07k6ltDuL1IIPqx.jpg",
      "popularity": 8.691,
      "adult": false,
      "known_for_department": "Acting"
    },
    {
      "id": 530025,
      "name": "Willow Shields",
      "profile_path": "/c9Zna579entVQBdx7kTtKJjl9CB.jpg",
      "popularity": 8.691,
      "adult": false,
      "known_for_department": "Acting"
    },
    {
      "id": 119337,
      "name": "Choi Dong-hoon",
      "profile_path": "/sn3f2zwi0BCaV0hWeD4aRWqNX5l.jpg",
      "popularity": 8.691,
      "adult": false,
      "known_for_department": "Directing"
    },
    {
      "id": 76696,
      "name": "Sarah Power",
      "profile_path": "/8VnpMflxnGpqR1jWu4NuUcWdziV.jpg",
      "popularity": 8.691,
      "adult": false,
      "known_for_department": "Acting"
    }
  ]
}