{
  "page": 173,
  "total_results": 10000,
  "total_pages": 500,
  "results": [
    {
      "id": 141956,
      "name": "Marc Evan Jackson",
      "profile_path": "/4TWP0nlhkxkZ5XzzZuz3RCoZjFX.jpg",
      "popularity": 15.554,
      "adult": false,
      "known_for_department": "Acting"
    },
    {
      "id": 1615061,
      "name": "Tina Tamashiro",
      "profile_path": "/u2OfpoFq4ZFaWnuCuH0JSpTo6hr.jpg",
      "popularity": 15.55,
      "adult": false,
      "known_for_department": "Acting"
    },
    {
      "id": 19265,
      "name": "Khandi Alexander",
      "profile_path": "/53IjZhkaywgsM0ZkDt3GJQtY5ls.jpg",
      "popularity": 15.55,
      "adult": false,
      "known_for_department": "Acting"
    },
    {
      "id": 5892,
      "name": "David Hewlett",
      "profile_path": "/hUcYyssAPCqnZ4GjolhOWXHTWSa.jpg",
      "popularity": 15.547,
      "adult": false,
      "known_for_department": "Acting"
    },
    {
      "id": 43774,
      "name": "Daniel Roebuck",
      "profile_path": "/y40aX3SdvUZwE7feNq77UMg3zge.jpg",
      "popularity": 15.545,
      "adult": false,
      "known_for_department": "Acting"
    },
    {
      "id": 21063,
      "name": "Pamela Adlon",
      "profile_path": "/e541ePtwZuHYP3zT0ANmpqUDFlw.jpg",
      "popularity": 15.534,
      "adult": false,
      "known_for_department": "Acting"
    },
    {
      "id": 1058956,
      "name": "Damla Sönmez",
      "profile_path": "/1XiAqioH6vBVnxGHWGjv6Ej8I5o.jpg",
      "popularity": 15.533,
      "adult": false,
      "known_for_department": "Acting"
    },
    {
      "id": 15903,
      "name": "George Carlin",
      "profile_path": "/6YKQHJzml6XviUADpSC6kfF56W9.jpg",
      "popularity": 15.533,
      "adult": false,
      "known_for_department": "Acting"
    },
    {
      "id": 506085,
      "name": "Sami Gayle",
      "profile_path": "/qdzSYk6tKvM9optzABPkfOcxFZ2.jpg",
      "popularity": 15.532,
      "adult": false,
      "known_for_department": "Acting"
    },
    {
      "id": 139161,
      "name": "Nora Waldstätten",
      "profile_path": "/6xMhvbU21OMNDdANXfcBpoCR4cN.jpg",
      "popularity": 15.532,
      "adult": false,
      "known_for_department": "Acting"
    },
    {
      "id": 37203,
      "name": "Jason Beghe",
      "profile_path": "/hrTwOPWek7nkPJgFhh6inFu7vSS.jpg",
      "popularity": 15.532,
      "adult": false,
      "known_for_department": "Acting"
    },
    {
      "id": 3091,
      "name": "Al Lettieri",
      "profile_path": "/fE5mEWPkkVJlCji0EoKht8PYw89.jpg",
      "popularity": 15.532,
      "adult": false,
      "known_for_department": "Acting"
    },
    {
      "id": 1369333,
      "name": "Amy Rutberg",
      "profile_path": "/yiqFU05UIEtPwk92TXVYClFzU5K.jpg",
      "popularity": 15.529,
      "adult": false,
      "known_for_department": "Acting"
    },
    {
      "id": 25532,
      "name": "Philip Jackson",
      "profile_path": "/eC7p4UAj6xB4TtQ4cPcIJtubPnw.jpg",
      "popularity": 15.529,
      "adult": false,
      "known_for_department": "Acting"
    },
    {
      "id": 220620,
      "name": "Alyssa Sutherland",
      "profile_path": "/femjkNZ7jTbcwz6LjoQQyRD5Mlc.jpg",
      "popularity": 15.527,
      "adult": false,
      "known_for_department": "Acting"
    },
    {
      "id": 54499,
      "name": "Briana Evigan",
      "profile_path": "/x927HOCSfZuuBtuQT2yAVHM5GSD.jpg",
      "popularity": 15.527,
      "adult": false,
      "known_for_department": "Acting"
    },
    {
      "id": 66446,
      "name": "Lucy Punch",
      "profile_path": "/jxNfHATSByLV89DysCMxYJPXJfE.jpg",
      "popularity": 15.523,
      "adult": false,
      "known_for_department": "Acting"
    },
    {
      "id": 2074237,
      "name": "Georgia Hirst",
      "profile_path": "/lnUhfcYBq1iCC5g8M6YmH4fhhTl.jpg",
      "popularity": 15.518,
      "adult": false,
      "known_for_department": "Acting"
    },
    {
      "id": 1299278,
      "name": "Kim Hye-eun",
      "profile_path": "/qoOOqPCwoNoZpZuelhOG1M4klgK.jpg",
      "popularity": 15.518,
      "adult": false,
      "known_for_department": "Acting"
    },
    {
      "id": 154332,
      "name": "Megyn Price",
      "profile_path": "/yCP4b1F0Q78NwtMajGZmpar4uSh.jpg",
      "popularity": 15.518,
      "adult": false,
      "known_for_department": "Acting"
    }
  ]
}