{
  "page": 441,
  "total_results": 10000,
  "total_pages": 500,
  "results": [
    {
      "id": 94820,
      "name": "Jessica DiCicco",
      "profile_path": "/7I9Ma8iV7KyiH7enKWquu7tGgah.jpg",
      "popularity": 7.8,
      "adult": false,
      "known_for_department": "Acting"
    },
    {
      "id": 1363555,
      "name": "Niseema Theillaud",
      "profile_path": "/c8NRwnrN8U9MGSLmnDdODiXP329.jpg",
      "popularity": 7.799,
      "adult": false,
      "known_for_department": "Acting"
    },
    {
      "id": 147505,
      "name": "Kim Sung-oh",
      "profile_path": "/cda0UsT4OUugqtn27NGQ2Wla6Yd.jpg",
      "popularity": 7.798,
      "adult": false,
      "known_for_department": "Acting"
    },
    {
      "id": 1644939,
      "name": "Lindsay Navarro",
      "profile_path": "/qdagEs4v7p7QfOnksX9mOSmh7pF.jpg",
      "popularity": 7.797,
      "adult": false,
      "known_for_department": "Acting"
    },
    {
      "id": 38707,
      "name": "Jason Dolley",
      "profile_path": "/uMx8ZOpU3jPUte6tvtfQls9HDC7.jpg",
      "popularity": 7.797,
      "adult": false,
      "known_for_department": "Acting"
    },
    {
      "id": 105562,
      "name": "Agnieszka Grochowska",
      "profile_path": "/9XBjnqR2PWw4KdcyTRaTZCFllxu.jpg",
      "popularity": 7.796,
      "adult": false,
      "known_for_department": "Acting"
    },
    {
      "id": 1802431,
      "name": "Hélène Barbry",
      "profile_path": "/3mcgIk0Lihguv8rYhxP6NcGcCET.jpg",
      "popularity": 7.795,
      "adult": false,
      "known_for_department": "Acting"
    },
    {
      "id": 1238951,
      "name": "Maya Mishalska",
      "profile_path": "/jKi6V2APtnxxOvRVQxeOdbaVca2.jpg",
      "popularity": 7.795,
      "adult": false,
      "known_for_department": "Acting"
    },
    {
      "id": 1212803,
      "name": "Joseph Marcell",
      "profile_path": "/mbjY5qqeT9aV7weLzvbN1ikPq0M.jpg",
      "popularity": 7.794,
      "adult": false,
      "known_for_department": "Acting"
    },
    {
      "id": 23495,
      "name": "Jonathan Jackson",
      "profile_path": "/qOfrqsoIOXuPpdh3aW0uif8UfcJ.jpg",
      "popularity": 7.793,
      "adult": false,
      "known_for_department": "Acting"
    },
    {
      "id": 1637039,
      "name": "Magdalena Lamparska",
      "profile_path": "/52eglsEGV71N5LcWj6I0YqGw8ke.jpg",
      "popularity": 7.792,
      "adult": false,
      "known_for_department": "Acting"
    },
    {
      "id": 1339108,
      "name": "Lena Klenke",
      "profile_path": "/ssSvTEnbtG3bLixVrLbf4xWxoDc.jpg",
      "popularity": 7.792,
      "adult": false,
      "known_for_department": "Acting"
    },
    {
      "id": 1280881,
      "name": "Tenzing Norgay Trainor",
      "profile_path": "/1mIj4EeFZHil1QClQY6W3fvfvIf.jpg",
      "popularity": 7.792,
      "adult": false,
      "known_for_department": "Acting"
    },
    {
      "id": 58648,
      "name": "Victor Rivers",
      "profile_path": "/9oWhFs2oRzaYOKqs0bGDZ2KGvuZ.jpg",
      "popularity": 7.792,
      "adult": false,
      "known_for_department": "Acting"
    },
    {
      "id": 84788,
      "name": "Kim Moo-yul",
      "profile_path": "/7SoxNZ826OzxV7WBplJWud8WhOr.jpg",
      "popularity": 7.791,
      "adult": false,
      "known_for_department": "Acting"
    },
    {
      "id": 62976,
      "name": "Eleanor Matsuura",
      "profile_path": "/8PTKH2LHXVxoxPm4kULlQ0OdwTg.jpg",
      "popularity": 7.791,
      "adult": false,
      "known_for_department": "Acting"
    },
    {
      "id": 18972,
      "name": "Danny Masterson",
      "profile_path": "/AeYYtZhDCqJqDmaFcA0eJV0bGSx.jpg",
      "popularity": 7.791,
      "adult": false,
      "known_for_department": "Acting"
    },
    {
      "id": 14328,
      "name": "Steve Kahan",
      "profile_path": "/clyTGAxNCmF0BxhnaZxbWDz7skt.jpg",
      "popularity": 7.791,
      "adult": false,
      "known_for_department": "Acting"
    },
    {
      "id": 154917,
      "name": "Al Sapienza",
      "profile_path": "/tqgr67aRg1OuuRhQFd8I3JduSRD.jpg",
      "popularity": 7.79,
      "adult": false,
      "known_for_department": "Acting"
    },
    {
      "id": 5319,
      "name": "Ron Cook",
      "profile_path": "/bYJ2x9FfQobon2Iai5CvoLgv1U5.jpg",
      "popularity": 7.79,
      "adult": false,
      "known_for_department": "Acting"
    }
  ]
}