{
  "page": 247,
  "total_results": 10000,
  "total_pages": 500,
  "results": [
    {
      "id": 972356,
      "name": "Luke Bracey",
      "profile_path": "/ot2h7IrXpC8XSnIZDSVsj2FQ5cx.jpg",
      "popularity": 10.708,
      "adult": false,
      "known_for_department": "Acting"
    },
    {
      "id": 41247,
      "name": "Len Cariou",
      "profile_path": "/9VJeCcxHkPkN4xH4izmwYHXRMy2.jpg",
      "popularity": 10.706,
      "adult": false,
      "known_for_department": "Acting"
    },
    {
      "id": 5077,
      "name": "Valeria Bruni Tedeschi",
      "profile_path": "/aUOCl9ejkoenABuTjcDpDtkbvD7.jpg",
      "popularity": 10.705,
      "adult": false,
      "known_for_department": "Acting"
    },
    {
      "id": 11109,
      "name": "Nick Frost",
      "profile_path": "/2CHS4t6miNGLgMQAjhFqb4fFuKS.jpg",
      "popularity": 10.704,
      "adult": false,
      "known_for_department": "Acting"
    },
    {
      "id": 1902690,
      "name": "Michelle Randolph",
      "profile_path": "/fLXXKLjhbMigNiiAoQIx7l2Fsht.jpg",
      "popularity": 10.702,
      "adult": false,
      "known_for_department": "Acting"
    },
    {
      "id": 1742596,
      "name": "Ritu Arya",
      "profile_path": "/bBRGCBAW0wNS7fQeGQroOeA60yw.jpg",
      "popularity": 10.7,
      "adult": false,
      "known_for_department": "Acting"
    },
    {
      "id": 2092879,
      "name": "Ella Balinska",
      "profile_path": "/bAk52rKKliEEqi9NVGKajUMeRez.jpg",
      "popularity": 10.699,
      "adult": false,
      "known_for_department": "Acting"
    },
    {
      "id": 10538,
      "name": "Vivien Leigh",
      "profile_path": "/6BqI3L41hwAwZM9ppTIBrwGT6jy.jpg",
      "popularity": 10.699,
      "adult": false,
      "known_for_department": "Acting"
    },
    {
      "id": 2104521,
      "name": "Lya Oussadit-Lessert",
      "profile_path": "/mqFkzFrMxqdmmzqey28toy6Dfc0.jpg",
      "popularity": 10.698,
      "adult": false,
      "known_for_department": "Acting"
    },
    {
      "id": 67206,
      "name": "Andrew Howard",
      "profile_path": "/kba1JeCUYHufjB933G5xPRhO8lV.jpg",
      "popularity": 10.698,
      "adult": false,
      "known_for_department": "Acting"
    },
    {
      "id": 62863,
      "name": "Jorma Taccone",
      "profile_path": "/x7x4NvDauuQ7HA6psLZYZ6m3zTd.jpg",
      "popularity": 10.698,
      "adult": false,
      "known_for_department": "Acting"
    },
    {
      "id": 51975,
      "name": "Laura Ramsey",
      "profile_path": "/dqfwHu82q7aGLS1QEtWUZYtXz03.jpg",
      "popularity": 10.698,
      "adult": false,
      "known_for_department": "Acting"
    },
    {
      "id": 43299,
      "name": "John DeSantis",
      "profile_path": "/sMsA0ox2wXkW2Y4uZvYpbpyaGsu.jpg",
      "popularity": 10.698,
      "adult": false,
      "known_for_department": "Acting"
    },
    {
      "id": 1461038,
      "name": "Jon Bass",
      "profile_path": "/2eo9pMyPhA9mBaSrNlD6UP3Nkyw.jpg",
      "popularity": 10.697,
      "adult": false,
      "known_for_department": "Acting"
    },
    {
      "id": 1158832,
      "name": "Chasty Ballesteros",
      "profile_path": "/qSg1EagcmG6UYotMATqHkCI7SNt.jpg",
      "popularity": 10.697,
      "adult": false,
      "known_for_department": "Acting"
    },
    {
      "id": 184924,
      "name": "Frances Tomelty",
      "profile_path": "/nZPZijCmdr5HvpiprTDAEbpwtlU.jpg",
      "popularity": 10.697,
      "adult": false,
      "known_for_department": "Acting"
    },
    {
      "id": 169725,
      "name": "Alaina Huffman",
      "profile_path": "/vqco0oYOBTHekppjsn88cFrIuKm.jpg",
      "popularity": 10.697,
      "adult": false,
      "known_for_department": "Acting"
    },
    {
      "id": 65196,
      "name": "Nadine Velazquez",
      "profile_path": "/uARYneOeME6qChGb029BAUQuHuM.jpg",
      "popularity": 10.696,
      "adult": false,
      "known_for_department": "Acting"
    },
    {
      "id": 1330918,
      "name": "Park Hyung-sik",
      "profile_path": "/A5j7LliVNXp1tmAXZm4JcRQojs3.jpg",
      "popularity": 10.695,
      "adult": false,
      "known_for_department": "Acting"
    },
    {
      "id": 83852,
      "name": "Liam James",
      "profile_path": "/a8qMiwUEbiohMnjwyMSOSrivUUE.jpg",
      "popularity": 10.695,
      "adult": false,
      "known_for_department": "Acting"
    }
  ]
}