{
  "page": 496,
  "total_results": 10000,
  "total_pages": 500,
  "results": [
    {
      "id": 2068596,
      "name": "Adriyan Rae",
      "profile_path": "/dUsffz7rNl1Le65oZBYuxY32LHY.jpg",
      "popularity": 6.88,
      "adult": false,
      "known_for_department": "Acting"
    },
    {
      "id": 1415918,
      "name": "Molly Windsor",
      "profile_path": "/mPDTgnj9Wio8NXX2f0pXxwyYY8z.jpg",
      "popularity": 6.88,
      "adult": false,
      "known_for_department": "Acting"
    },
    {
      "id": 956575,
      "name": "Wong Yat-fei",
      "profile_path": "/eMpNYfWMxmIPWvDd1npajeDweI7.jpg",
      "popularity": 6.88,
      "adult": false,
      "known_for_department": "Acting"
    },
    {
      "id": 18649,
      "name": "John Randolph",
      "profile_path": "/lJzBpptZD3d39y9WpNk7i7ibvOc.jpg",
      "popularity": 6.88,
      "adult": false,
      "known_for_department": "Acting"
    },
    {
      "id": 17114,
      "name": "John Cameron Mitchell",
      "profile_path": "/iDyhkjtgy7U8xl9tKk9xcJA3yEY.jpg",
      "popularity": 6.88,
      "adult": false,
      "known_for_department": "Acting"
    },
    {
      "id": 1887410,
      "name": "Ryoko Maekawa",
      "profile_path": "/deIA9iMu7btUpm7gVqid1pTNXIT.jpg",
      "popularity": 6.878,
      "adult": false,
      "known_for_department": "Acting"
    },
    {
      "id": 1350418,
      "name": "Yusuke Kobayashi",
      "profile_path": "/r5hRCRBz1kMPBIVERUYPzwHPaIN.jpg",
      "popularity": 6.878,
      "adult": false,
      "known_for_department": "Acting"
    },
    {
      "id": 70820,
      "name": "John Payne",
      "profile_path": "/2PRAP6XPLMQFK5eeJ63A7g0jvw.jpg",
      "popularity": 6.878,
      "adult": false,
      "known_for_department": "Acting"
    },
    {
      "id": 21490,
      "name": "Peter Onorati",
      "profile_path": "/1ZrzYcnGcoMKA0jmcoC15GsrOxz.jpg",
      "popularity": 6.878,
      "adult": false,
      "known_for_department": "Acting"
    },
    {
      "id": 229606,
      "name": "Monica Dolan",
      "profile_path": "/lR61knP6P7ESFYUapWNhG22TA3s.jpg",
      "popularity": 6.877,
      "adult": false,
      "known_for_department": "Acting"
    },
    {
      "id": 174982,
      "name": "Neil Pearson",
      "profile_path": "/sS1WuIU3l6o6QcDIkGdtWK8R3Wn.jpg",
      "popularity": 6.877,
      "adult": false,
      "known_for_department": "Acting"
    },
    {
      "id": 2013328,
      "name": "Carolyn Cronenberg",
      "profile_path": "",
      "popularity": 6.876,
      "adult": false,
      "known_for_department": "Directing"
    },
    {
      "id": 1252339,
      "name": "Ham Eun-jeong",
      "profile_path": "/5sra4rsKJknm3ov7NG94PCd1ciC.jpg",
      "popularity": 6.876,
      "adult": false,
      "known_for_department": "Acting"
    },
    {
      "id": 32203,
      "name": "Stephen Moyer",
      "profile_path": "/xprwOCXa2cNkjhrGtcJp0VfJMlZ.jpg",
      "popularity": 6.876,
      "adult": false,
      "known_for_department": "Acting"
    },
    {
      "id": 26279,
      "name": "Manuela Vellés",
      "profile_path": "/7OOgSPH8frF5C8x7NYN19mOmbGN.jpg",
      "popularity": 6.876,
      "adult": false,
      "known_for_department": "Acting"
    },
    {
      "id": 1411632,
      "name": "David DeSantos",
      "profile_path": "/fjITIoZXMiJoT53cY7NkiTpeUcl.jpg",
      "popularity": 6.875,
      "adult": false,
      "known_for_department": "Acting"
    },
    {
      "id": 38707,
      "name": "Jason Dolley",
      "profile_path": "/uMx8ZOpU3jPUte6tvtfQls9HDC7.jpg",
      "popularity": 6.875,
      "adult": false,
      "known_for_department": "Acting"
    },
    {
      "id": 25972,
      "name": "Melina Kanakaredes",
      "profile_path": "/wA41eJETN2U2WUE0EXBsHeIbS67.jpg",
      "popularity": 6.875,
      "adult": false,
      "known_for_department": "Acting"
    },
    {
      "id": 7465,
      "name": "Carrie Preston",
      "profile_path": "/cxqAk6PaZJ92mb9taka3XlcVlUU.jpg",
      "popularity": 6.875,
      "adult": false,
      "known_for_department": "Acting"
    },
    {
      "id": 2354142,
      "name": "Ruth Goodwin",
      "profile_path": "/wcI7ASJfGk5L14WurK7MTA2buvF.jpg",
      "popularity": 6.874,
      "adult": false,
      "known_for_department": "Acting"
    }
  ]
}