{
  "page": 294,
  "total_results": 10000,
  "total_pages": 500,
  "results": [
    {
      "id": 210773,
      "name": "Rutina Wesley",
      "profile_path": "/7URGlymb9VjzefxiAUtKOMshZZq.jpg",
      "popularity": 8.783,
      "adult": false,
      "known_for_department": "Acting"
    },
    {
      "id": 1058633,
      "name": "Peri Baumeister",
      "profile_path": "/bfWBGT1b8kB22hhUc4WQWWUvzln.jpg",
      "popularity": 8.782,
      "adult": false,
      "known_for_department": "Acting"
    },
    {
      "id": 104410,
      "name": "June Chadwick",
      "profile_path": "/erU3RGLRvOSeHQZJJ7ccSafBJKF.jpg",
      "popularity": 8.781,
      "adult": false,
      "known_for_department": "Acting"
    },
    {
      "id": 1860101,
      "name": "Lee Elijah",
      "profile_path": "/hbgCp7KBMlP85CLSaGUKG2xJnpe.jpg",
      "popularity": 8.778,
      "adult": false,
      "known_for_department": "Acting"
    },
    {
      "id": 15385,
      "name": "Alida Valli",
      "profile_path": "/ze8OiV87TYR4PmyuNIobl02ODjo.jpg",
      "popularity": 8.776,
      "adult": false,
      "known_for_department": "Acting"
    },
    {
      "id": 3162,
      "name": "Billy Gray",
      "profile_path": "/8gqewHt3M3Q9HeZZclNmGGth2hL.jpg",
      "popularity": 8.775,
      "adult": false,
      "known_for_department": "Acting"
    },
    {
      "id": 62042,
      "name": "Carole Davis",
      "profile_path": "/qsAqnsugOYNBLOBcwrTkmVLHrUt.jpg",
      "popularity": 8.774,
      "adult": false,
      "known_for_department": "Acting"
    },
    {
      "id": 1072,
      "name": "James Tolkan",
      "profile_path": "/euEktcyVXm1pq5UBC16v3zuBq7J.jpg",
      "popularity": 8.774,
      "adult": false,
      "known_for_department": "Acting"
    },
    {
      "id": 17782,
      "name": "Colm Meaney",
      "profile_path": "/guL6RJdlRMtOJN3LoaY3G8hG4Rd.jpg",
      "popularity": 8.773,
      "adult": false,
      "known_for_department": "Acting"
    },
    {
      "id": 2250359,
      "name": "Jiang Zixin",
      "profile_path": "/tsYnvAz1zWsvNQ0FgcjEhdNvDlB.jpg",
      "popularity": 8.772,
      "adult": false,
      "known_for_department": "Acting"
    },
    {
      "id": 11159,
      "name": "Cheech Marin",
      "profile_path": "/eecHDNRn9K80ZcuSocsMhQb2G1i.jpg",
      "popularity": 8.772,
      "adult": false,
      "known_for_department": "Acting"
    },
    {
      "id": 1286,
      "name": "Julia Winter",
      "profile_path": "/3HKwgDkcPIVipD7PV1WaJtrUxzu.jpg",
      "popularity": 8.772,
      "adult": false,
      "known_for_department": "Acting"
    },
    {
      "id": 101367,
      "name": "Yuki Uchida",
      "profile_path": "/y6de9FCwdsUGvAsNcamicxovins.jpg",
      "popularity": 8.77,
      "adult": false,
      "known_for_department": "Acting"
    },
    {
      "id": 35689,
      "name": "Keenen Ivory Wayans",
      "profile_path": "/e9XRdXolDV8RjGPHPXH6IISDTSP.jpg",
      "popularity": 8.77,
      "adult": false,
      "known_for_department": "Acting"
    },
    {
      "id": 2239782,
      "name": "Ryu Kyung-soo",
      "profile_path": "/yAHJk1EyGdGidl42ejLROxYkPPK.jpg",
      "popularity": 8.769,
      "adult": false,
      "known_for_department": "Acting"
    },
    {
      "id": 77330,
      "name": "Kenan Thompson",
      "profile_path": "/vHPhDGc1om91TzoIQ4zMscpNmxF.jpg",
      "popularity": 8.767,
      "adult": false,
      "known_for_department": "Acting"
    },
    {
      "id": 31005,
      "name": "Noble Willingham",
      "profile_path": "/70HEA9aOmmPmTeCvxXqJC6KGHaZ.jpg",
      "popularity": 8.767,
      "adult": false,
      "known_for_department": "Acting"
    },
    {
      "id": 1614208,
      "name": "Wang Ruizi",
      "profile_path": "/tBNtYS0IDRCQJajLrgAO5oC5bbY.jpg",
      "popularity": 8.766,
      "adult": false,
      "known_for_department": "Acting"
    },
    {
      "id": 42706,
      "name": "Nicholas Lea",
      "profile_path": "/z9H2GArx5gU6iZBpiqSMJHE2VAQ.jpg",
      "popularity": 8.766,
      "adult": false,
      "known_for_department": "Acting"
    },
    {
      "id": 464228,
      "name": "Aoba Kawai",
      "profile_path": "/uwco35JnqlaFLM4nmy5BMsmI8i0.jpg",
      "popularity": 8.765,
      "adult": false,
      "known_for_department": "Acting"
    }
  ]
}