{
  "page": 237,
  "total_results": 10000,
  "total_pages": 500,
  "results": [
    {
      "id": 67711,
      "name": "French Stewart",
      "profile_path": "/58v2ob0bzhvTIBwLcLx8SKgrwPh.jpg",
      "popularity": 10.874,
      "adult": false,
      "known_for_department": "Acting"
    },
    {
      "id": 2735723,
      "name": "Ye Seul",
      "profile_path": "/A5HuFCWXKyKcsYZBzvTeJBzoSu6.jpg",
      "popularity": 10.872,
      "adult": false,
      "known_for_department": "Acting"
    },
    {
      "id": 929122,
      "name": "Esom",
      "profile_path": "/6JsHYr0qz5XPzvKRrMTojRmxNjF.jpg",
      "popularity": 10.87,
      "adult": false,
      "known_for_department": "Acting"
    },
    {
      "id": 1256310,
      "name": "Boncuk Yilmaz",
      "profile_path": "/zOBcaBPmWD3bY0zcmJKuLVwyYbC.jpg",
      "popularity": 10.869,
      "adult": false,
      "known_for_department": "Acting"
    },
    {
      "id": 979412,
      "name": "Matthew Cardarople",
      "profile_path": "/xhKO4iMPnwQS1GeDiY8vOyLFa8x.jpg",
      "popularity": 10.865,
      "adult": false,
      "known_for_department": "Acting"
    },
    {
      "id": 11961,
      "name": "Chintara Sukapatana",
      "profile_path": "/kY6nSy9R2n0VhIdTNkKbhjS1uMI.jpg",
      "popularity": 10.865,
      "adult": false,
      "known_for_department": "Acting"
    },
    {
      "id": 70785,
      "name": "Anita Briem",
      "profile_path": "/8M6MkLKpAXKRoYlhOH5LzBhBGFv.jpg",
      "popularity": 10.864,
      "adult": false,
      "known_for_department": "Acting"
    },
    {
      "id": 44810,
      "name": "Cassandra Peterson",
      "profile_path": "/ykrDhr0lBHjVLjxvclbpvHaEi5L.jpg",
      "popularity": 10.864,
      "adult": false,
      "known_for_department": "Acting"
    },
    {
      "id": 208539,
      "name": "Anna Hopkins",
      "profile_path": "/uL44Lc0ql6y3bmuGz9r7NvhBSKR.jpg",
      "popularity": 10.863,
      "adult": false,
      "known_for_department": "Acting"
    },
    {
      "id": 12329,
      "name": "Vittorio De Sica",
      "profile_path": "/p793imBa2qIqTKyuXynphs5daYJ.jpg",
      "popularity": 10.862,
      "adult": false,
      "known_for_department": "Directing"
    },
    {
      "id": 40595,
      "name": "Mike Henry",
      "profile_path": "/ivTRuqlErfqp4tXooiRqthqEjil.jpg",
      "popularity": 10.86,
      "adult": false,
      "known_for_department": "Acting"
    },
    {
      "id": 27643,
      "name": "Marco Leonardi",
      "profile_path": "/5VVhO9rPvRgKsZME2gZKtG9WgWD.jpg",
      "popularity": 10.858,
      "adult": false,
      "known_for_department": "Acting"
    },
    {
      "id": 38425,
      "name": "Amber Valletta",
      "profile_path": "/8QrEYhULn1JuCo34Au79cowHaQn.jpg",
      "popularity": 10.857,
      "adult": false,
      "known_for_department": "Acting"
    },
    {
      "id": 51751,
      "name": "Susan Walters",
      "profile_path": "/i3XQLCbYrNaa1yng2hLjaG5LGJX.jpg",
      "popularity": 10.855,
      "adult": false,
      "known_for_department": "Acting"
    },
    {
      "id": 20330,
      "name": "Yuriko Ishida",
      "profile_path": "/cADoBCi603Chz2IaxcwWT2mNwCf.jpg",
      "popularity": 10.855,
      "adult": false,
      "known_for_department": "Acting"
    },
    {
      "id": 41785,
      "name": "Joel Tobeck",
      "profile_path": "/8pzK6mGsSxZ4hGAx1KFhsVRepT4.jpg",
      "popularity": 10.853,
      "adult": false,
      "known_for_department": "Acting"
    },
    {
      "id": 34521,
      "name": "Maurice LaMarche",
      "profile_path": "/qCiL3EYAhLcNo0rNj5pczWo9MwG.jpg",
      "popularity": 10.853,
      "adult": false,
      "known_for_department": "Acting"
    },
    {
      "id": 20354,
      "name": "Amber Tamblyn",
      "profile_path": "/bzw0lxvtbEnYT7fZ8fn6NeSzMn9.jpg",
      "popularity": 10.852,
      "adult": false,
      "known_for_department": "Acting"
    },
    {
      "id": 122876,
      "name": "Laura Bertram",
      "profile_path": "/f726f8MdTOtke12QtNjvGbXVjVQ.jpg",
      "popularity": 10.85,
      "adult": false,
      "known_for_department": "Acting"
    },
    {
      "id": 2194273,
      "name": "Evan Roderick",
      "profile_path": "/nyvCM1XGkh3bAIx1IFgZFuBfpVh.jpg",
      "popularity": 10.849,
      "adult": false,
      "known_for_department": "Acting"
    }
  ]
}